{
    "stew": [
        {
            "_id": {
                "matchId": "6697f074d86b270007ae0e5a",
                "playerId": "2be37d17-f9fb-42e2-8143-bcdb5f1239b2"
            },
            "created_at": 1721233524552,
            "updated_at": 1721233615061,
            "i31": "7",
            "i30": "119",
            "i33": "2",
            "i10": "1",
            "i32": "2",
            "i13": "4",
            "i35": "2",
            "i34": "2",
            "i37": "0",
            "i15": "0",
            "i36": "0",
            "i14": "0",
            "i39": "4",
            "i38": "2",
            "i16": "0",
            "nickname": "stew",
            "playerId": "2be37d17-f9fb-42e2-8143-bcdb5f1239b2",
            "i40": "2",
            "i20": "1533",
            "i22": "1",
            "i21": "5",
            "i24": "0",
            "i23": "0",
            "i26": "0",
            "i6": "10",
            "i25": "1",
            "i28": "16",
            "i7": "6",
            "i8": "15",
            "i27": "12",
            "i9": "0",
            "i29": "7",
            "c10": "66.7",
            "c2": "0.67",
            "c3": "0.43",
            "c4": "40",
            "c1": "1",
            "i19": "0",
            "teamId": "bac03b15-c6a8-4388-8013-601ec5156028",
            "i3": "9",
            "i4": "4",
            "i5": "team_fl0m",
            "premade": false,
            "c5": "13",
            "bestOf": "2",
            "competitionId": "3aced33b-f21c-450c-91d5-10535164e0ab",
            "date": 1721233524000,
            "game": "cs2",
            "gameMode": "5v5",
            "i0": "NA",
            "i1": "de_dust2",
            "i12": "23",
            "i18": "13 / 10",
            "i2": "bac03b15-c6a8-4388-8013-601ec5156028",
            "matchId": "1-98987da6-4bb3-4d26-9a6a-ce6f2333c799",
            "matchRound": "1",
            "played": "1",
            "status": "APPLIED",
            "elo": "2698"
        }
    ]
}